{
    "A": {
        "win": {
            "B": 79,
            "C": 67,
            "D": 67
        },
        "null": {
            "B": 0,
            "C": 0,
            "D": 0
        },
        "lose": {
            "B": 73,
            "C": 77,
            "D": 59
        }
    },
    "B": {
        "win": {
            "A": 73,
            "C": 142,
            "D": 102
        },
        "null": {
            "A": 0,
            "C": 0,
            "D": 0
        },
        "lose": {
            "A": 79,
            "C": 102,
            "D": 127
        }
    },
    "C": {
        "win": {
            "A": 77,
            "B": 102,
            "D": 81
        },
        "null": {
            "A": 0,
            "B": 0,
            "D": 0
        },
        "lose": {
            "A": 67,
            "B": 142,
            "D": 102
        }
    },
    "D": {
        "win": {
            "A": 59,
            "B": 127,
            "C": 102
        },
        "null": {
            "A": 0,
            "B": 0,
            "C": 0
        },
        "lose": {
            "A": 67,
            "B": 102,
            "C": 81
        }
    }
}