{
    "Ranking": "2",
    "Number Of Seats": 1,
    "Stats": {
        "Votes Needed to Win": 380,
        "Initial Score Table": {
            "1": 98,
            "2": 145,
            "3": 58,
            "4": 40,
            "5": 141,
            "6": 33,
            "7": 60,
            "8": 166
        },
        "Candidates elected from first round": {},
        "Candidates eliminated from first round": {
            "0": "1",
            "1": "2",
            "2": "3",
            "3": "4",
            "4": "5",
            "5": "6",
            "6": "7",
            "7": "8"
        },
        "Completion Method": "Schulze Margin",
        "Condorcet Completion Method Stats": {
            "Pairwise": {
                "0": {
                    "win": {
                        "1": 1042548535899,
                        "2": 1084389948711,
                        "3": 951892141473,
                        "4": 1161099205533,
                        "5": 1039061751498,
                        "6": 1014654260691,
                        "7": 1056495673503
                    },
                    "null": {
                        "1": 0,
                        "2": 0,
                        "3": 0,
                        "4": 0,
                        "5": 0,
                        "6": 0,
                        "7": 0
                    },
                    "lose": {
                        "1": 850775393844,
                        "2": 735711508611,
                        "3": 1126231361523,
                        "4": 652028682987,
                        "5": 878669669052,
                        "6": 1059982457904,
                        "7": 826367903037
                    }
                },
                "1": {
                    "win": {
                        "0": 850775393844,
                        "2": 822881118636,
                        "3": 606700485774,
                        "4": 843801825042,
                        "5": 732224724210,
                        "6": 704330449002,
                        "7": 753145430616
                    },
                    "null": {
                        "0": 0,
                        "2": 0,
                        "3": 0,
                        "4": 0,
                        "5": 0,
                        "6": 0,
                        "7": 0
                    },
                    "lose": {
                        "0": 1042548535899,
                        "2": 805447196631,
                        "3": 1283136659568,
                        "4": 756632215017,
                        "5": 889130022255,
                        "6": 1161099205533,
                        "7": 944918572671
                    }
                },
                "2": {
                    "win": {
                        "0": 735711508611,
                        "1": 805447196631,
                        "3": 592753348170,
                        "4": 676436173794,
                        "5": 638081545383,
                        "6": 575319426165,
                        "7": 613674054576
                    },
                    "null": {
                        "0": 0,
                        "1": 0,
                        "3": 0,
                        "4": 0,
                        "5": 0,
                        "6": 0,
                        "7": 0
                    },
                    "lose": {
                        "0": 1084389948711,
                        "1": 822881118636,
                        "3": 1272676306365,
                        "4": 774066137022,
                        "5": 1018141045092,
                        "6": 1220374540350,
                        "7": 972812847879
                    }
                },
                "3": {
                    "win": {
                        "0": 1126231361523,
                        "1": 1283136659568,
                        "2": 1272676306365,
                        "4": 1227348109152,
                        "5": 1073929595508,
                        "6": 1004193907488,
                        "7": 1112284223919
                    },
                    "null": {
                        "0": 0,
                        "1": 0,
                        "2": 0,
                        "4": 0,
                        "5": 0,
                        "6": 0,
                        "7": 0
                    },
                    "lose": {
                        "0": 951892141473,
                        "1": 606700485774,
                        "2": 592753348170,
                        "4": 624134407779,
                        "5": 833341471839,
                        "6": 1007680691889,
                        "7": 808933981032
                    }
                },
                "4": {
                    "win": {
                        "0": 652028682987,
                        "1": 756632215017,
                        "2": 774066137022,
                        "3": 624134407779,
                        "5": 620647623378,
                        "6": 529991228952,
                        "7": 564859072962
                    },
                    "null": {
                        "0": 0,
                        "1": 0,
                        "2": 0,
                        "3": 0,
                        "5": 0,
                        "6": 0,
                        "7": 0
                    },
                    "lose": {
                        "0": 1161099205533,
                        "1": 843801825042,
                        "2": 676436173794,
                        "3": 1227348109152,
                        "5": 1011167476290,
                        "6": 1213400971548,
                        "7": 969326063478
                    }
                },
                "5": {
                    "win": {
                        "0": 878669669052,
                        "1": 889130022255,
                        "2": 1018141045092,
                        "3": 833341471839,
                        "4": 1011167476290,
                        "6": 756632215017,
                        "7": 746171861814
                    },
                    "null": {
                        "0": 0,
                        "1": 0,
                        "2": 0,
                        "3": 0,
                        "4": 0,
                        "6": 0,
                        "7": 0
                    },
                    "lose": {
                        "0": 1039061751498,
                        "1": 732224724210,
                        "2": 638081545383,
                        "3": 1073929595508,
                        "4": 620647623378,
                        "6": 1119257792721,
                        "7": 944918572671
                    }
                },
                "6": {
                    "win": {
                        "0": 1059982457904,
                        "1": 1161099205533,
                        "2": 1220374540350,
                        "3": 1007680691889,
                        "4": 1213400971548,
                        "5": 1119257792721,
                        "7": 1046035320300
                    },
                    "null": {
                        "0": 0,
                        "1": 0,
                        "2": 0,
                        "3": 0,
                        "4": 0,
                        "5": 0,
                        "7": 0
                    },
                    "lose": {
                        "0": 1014654260691,
                        "1": 704330449002,
                        "2": 575319426165,
                        "3": 1004193907488,
                        "4": 529991228952,
                        "5": 756632215017,
                        "7": 808933981032
                    }
                },
                "7": {
                    "win": {
                        "0": 826367903037,
                        "1": 944918572671,
                        "2": 972812847879,
                        "3": 808933981032,
                        "4": 969326063478,
                        "5": 944918572671,
                        "6": 808933981032
                    },
                    "null": {
                        "0": 0,
                        "1": 0,
                        "2": 0,
                        "3": 0,
                        "4": 0,
                        "5": 0,
                        "6": 0
                    },
                    "lose": {
                        "0": 1056495673503,
                        "1": 753145430616,
                        "2": 613674054576,
                        "3": 1112284223919,
                        "4": 564859072962,
                        "5": 746171861814,
                        "6": 1046035320300
                    }
                }
            },
            "Stats": {
                "0": {
                    "1": 191773142055,
                    "2": 348678440100,
                    "3": 0,
                    "4": 509070522546,
                    "5": 198746710857,
                    "6": 0,
                    "7": 230127770466
                },
                "1": {
                    "0": 0,
                    "2": 87169610025,
                    "3": 0,
                    "4": 87169610025,
                    "5": 0,
                    "6": 0,
                    "7": 0
                },
                "2": {
                    "0": 0,
                    "1": 0,
                    "3": 0,
                    "4": 0,
                    "5": 0,
                    "6": 0,
                    "7": 0
                },
                "3": {
                    "0": 174339220050,
                    "1": 676436173794,
                    "2": 679922958195,
                    "4": 603213701373,
                    "5": 240588123669,
                    "6": 0,
                    "7": 303350242887
                },
                "4": {
                    "0": 0,
                    "1": 0,
                    "2": 97629963228,
                    "3": 0,
                    "5": 0,
                    "6": 0,
                    "7": 0
                },
                "5": {
                    "0": 0,
                    "1": 156905298045,
                    "2": 380059499709,
                    "3": 0,
                    "4": 390519852912,
                    "6": 0,
                    "7": 0
                },
                "6": {
                    "0": 45328197213,
                    "1": 456768756531,
                    "2": 645055114185,
                    "3": 3486784401,
                    "4": 683409742596,
                    "5": 362625577704,
                    "7": 237101339268
                },
                "7": {
                    "0": 0,
                    "1": 191773142055,
                    "2": 359138793303,
                    "3": 0,
                    "4": 404466990516,
                    "5": 198746710857,
                    "6": 0
                }
            }
        },
        "Outcomes": {
            "0": {
                "0": "8"
            },
            "1": {
                "0": "7"
            },
            "2": {
                "0": "6"
            },
            "3": {
                "0": "5"
            },
            "4": {
                "0": "4"
            },
            "5": {
                "0": "3"
            },
            "6": {
                "0": "2"
            },
            "7": {
                "0": "1"
            }
        },
        "Outcomes Comparison": {
            "Outcome N° 0 compared to Outcome N° 1": {
                "candidates_excluded": {
                    "0": "1",
                    "1": "2",
                    "2": "3",
                    "3": "4",
                    "4": "5",
                    "5": "6"
                },
                "scores_after_exclusion": {
                    "7": 244,
                    "8": 299
                },
                "scores_after_surplus": {
                    "7": 244,
                    "8": 299
                },
                "outcomes_scores": {
                    "0": 299,
                    "1": 244
                }
            },
            "Outcome N° 0 compared to Outcome N° 2": {
                "candidates_excluded": {
                    "0": "1",
                    "1": "2",
                    "2": "3",
                    "3": "4",
                    "4": "5",
                    "5": "7"
                },
                "scores_after_exclusion": {
                    "6": 211,
                    "8": 311
                },
                "scores_after_surplus": {
                    "6": 211,
                    "8": 311
                },
                "outcomes_scores": {
                    "0": 311,
                    "2": 211
                }
            },
            "Outcome N° 0 compared to Outcome N° 3": {
                "candidates_excluded": {
                    "0": "1",
                    "1": "2",
                    "2": "3",
                    "3": "4",
                    "4": "6",
                    "5": "7"
                },
                "scores_after_exclusion": {
                    "5": 323,
                    "8": 273
                },
                "scores_after_surplus": {
                    "5": 323,
                    "8": 273
                },
                "outcomes_scores": {
                    "0": 273,
                    "3": 323
                }
            },
            "Outcome N° 0 compared to Outcome N° 4": {
                "candidates_excluded": {
                    "0": "1",
                    "1": "2",
                    "2": "3",
                    "3": "5",
                    "4": "6",
                    "5": "7"
                },
                "scores_after_exclusion": {
                    "4": 187,
                    "8": 333
                },
                "scores_after_surplus": {
                    "4": 187,
                    "8": 333
                },
                "outcomes_scores": {
                    "0": 333,
                    "4": 187
                }
            },
            "Outcome N° 0 compared to Outcome N° 5": {
                "candidates_excluded": {
                    "0": "1",
                    "1": "2",
                    "2": "4",
                    "3": "5",
                    "4": "6",
                    "5": "7"
                },
                "scores_after_exclusion": {
                    "3": 252,
                    "8": 298
                },
                "scores_after_surplus": {
                    "3": 252,
                    "8": 298
                },
                "outcomes_scores": {
                    "0": 298,
                    "5": 252
                }
            },
            "Outcome N° 0 compared to Outcome N° 6": {
                "candidates_excluded": {
                    "0": "1",
                    "1": "3",
                    "2": "4",
                    "3": "5",
                    "4": "6",
                    "5": "7"
                },
                "scores_after_exclusion": {
                    "2": 304,
                    "8": 291
                },
                "scores_after_surplus": {
                    "2": 304,
                    "8": 291
                },
                "outcomes_scores": {
                    "0": 291,
                    "6": 304
                }
            },
            "Outcome N° 0 compared to Outcome N° 7": {
                "candidates_excluded": {
                    "0": "2",
                    "1": "3",
                    "2": "4",
                    "3": "5",
                    "4": "6",
                    "5": "7"
                },
                "scores_after_exclusion": {
                    "1": 237,
                    "8": 303
                },
                "scores_after_surplus": {
                    "1": 237,
                    "8": 303
                },
                "outcomes_scores": {
                    "0": 303,
                    "7": 237
                }
            },
            "Outcome N° 1 compared to Outcome N° 2": {
                "candidates_excluded": {
                    "0": "1",
                    "1": "2",
                    "2": "3",
                    "3": "4",
                    "4": "5",
                    "5": "8"
                },
                "scores_after_exclusion": {
                    "6": 231,
                    "7": 236
                },
                "scores_after_surplus": {
                    "6": 231,
                    "7": 236
                },
                "outcomes_scores": {
                    "1": 236,
                    "2": 231
                }
            },
            "Outcome N° 1 compared to Outcome N° 3": {
                "candidates_excluded": {
                    "0": "1",
                    "1": "2",
                    "2": "3",
                    "3": "4",
                    "4": "6",
                    "5": "8"
                },
                "scores_after_exclusion": {
                    "5": 368,
                    "7": 174
                },
                "scores_after_surplus": {
                    "5": 368,
                    "7": 174
                },
                "outcomes_scores": {
                    "1": 174,
                    "3": 368
                }
            },
            "Outcome N° 1 compared to Outcome N° 4": {
                "candidates_excluded": {
                    "0": "1",
                    "1": "2",
                    "2": "3",
                    "3": "5",
                    "4": "6",
                    "5": "8"
                },
                "scores_after_exclusion": {
                    "4": 217,
                    "7": 242
                },
                "scores_after_surplus": {
                    "4": 217,
                    "7": 242
                },
                "outcomes_scores": {
                    "1": 242,
                    "4": 217
                }
            },
            "Outcome N° 1 compared to Outcome N° 5": {
                "candidates_excluded": {
                    "0": "1",
                    "1": "2",
                    "2": "4",
                    "3": "5",
                    "4": "6",
                    "5": "8"
                },
                "scores_after_exclusion": {
                    "3": 255,
                    "7": 210
                },
                "scores_after_surplus": {
                    "3": 255,
                    "7": 210
                },
                "outcomes_scores": {
                    "1": 210,
                    "5": 255
                }
            },
            "Outcome N° 1 compared to Outcome N° 6": {
                "candidates_excluded": {
                    "0": "1",
                    "1": "3",
                    "2": "4",
                    "3": "5",
                    "4": "6",
                    "5": "8"
                },
                "scores_after_exclusion": {
                    "2": 333,
                    "7": 202
                },
                "scores_after_surplus": {
                    "2": 333,
                    "7": 202
                },
                "outcomes_scores": {
                    "1": 202,
                    "6": 333
                }
            },
            "Outcome N° 1 compared to Outcome N° 7": {
                "candidates_excluded": {
                    "0": "2",
                    "1": "3",
                    "2": "4",
                    "3": "5",
                    "4": "6",
                    "5": "8"
                },
                "scores_after_exclusion": {
                    "1": 271,
                    "7": 216
                },
                "scores_after_surplus": {
                    "1": 271,
                    "7": 216
                },
                "outcomes_scores": {
                    "1": 216,
                    "7": 271
                }
            },
            "Outcome N° 2 compared to Outcome N° 3": {
                "candidates_excluded": {
                    "0": "1",
                    "1": "2",
                    "2": "3",
                    "3": "4",
                    "4": "7",
                    "5": "8"
                },
                "scores_after_exclusion": {
                    "5": 365,
                    "6": 170
                },
                "scores_after_surplus": {
                    "5": 365,
                    "6": 170
                },
                "outcomes_scores": {
                    "2": 170,
                    "3": 365
                }
            },
            "Outcome N° 2 compared to Outcome N° 4": {
                "candidates_excluded": {
                    "0": "1",
                    "1": "2",
                    "2": "3",
                    "3": "5",
                    "4": "7",
                    "5": "8"
                },
                "scores_after_exclusion": {
                    "4": 222,
                    "6": 194
                },
                "scores_after_surplus": {
                    "4": 222,
                    "6": 194
                },
                "outcomes_scores": {
                    "2": 194,
                    "4": 222
                }
            },
            "Outcome N° 2 compared to Outcome N° 5": {
                "candidates_excluded": {
                    "0": "1",
                    "1": "2",
                    "2": "4",
                    "3": "5",
                    "4": "7",
                    "5": "8"
                },
                "scores_after_exclusion": {
                    "3": 292,
                    "6": 183
                },
                "scores_after_surplus": {
                    "3": 292,
                    "6": 183
                },
                "outcomes_scores": {
                    "2": 183,
                    "5": 292
                }
            },
            "Outcome N° 2 compared to Outcome N° 6": {
                "candidates_excluded": {
                    "0": "1",
                    "1": "3",
                    "2": "4",
                    "3": "5",
                    "4": "7",
                    "5": "8"
                },
                "scores_after_exclusion": {
                    "2": 350,
                    "6": 165
                },
                "scores_after_surplus": {
                    "2": 350,
                    "6": 165
                },
                "outcomes_scores": {
                    "2": 165,
                    "6": 350
                }
            },
            "Outcome N° 2 compared to Outcome N° 7": {
                "candidates_excluded": {
                    "0": "2",
                    "1": "3",
                    "2": "4",
                    "3": "5",
                    "4": "7",
                    "5": "8"
                },
                "scores_after_exclusion": {
                    "1": 279,
                    "6": 176
                },
                "scores_after_surplus": {
                    "1": 279,
                    "6": 176
                },
                "outcomes_scores": {
                    "2": 176,
                    "7": 279
                }
            },
            "Outcome N° 3 compared to Outcome N° 4": {
                "candidates_excluded": {
                    "0": "1",
                    "1": "2",
                    "2": "3",
                    "3": "6",
                    "4": "7",
                    "5": "8"
                },
                "scores_after_exclusion": {
                    "4": 179,
                    "5": 352
                },
                "scores_after_surplus": {
                    "4": 179,
                    "5": 352
                },
                "outcomes_scores": {
                    "3": 352,
                    "4": 179
                }
            },
            "Outcome N° 3 compared to Outcome N° 5": {
                "candidates_excluded": {
                    "0": "1",
                    "1": "2",
                    "2": "4",
                    "3": "6",
                    "4": "7",
                    "5": "8"
                },
                "scores_after_exclusion": {
                    "3": 239,
                    "5": 308
                },
                "scores_after_surplus": {
                    "3": 239,
                    "5": 308
                },
                "outcomes_scores": {
                    "3": 308,
                    "5": 239
                }
            },
            "Outcome N° 3 compared to Outcome N° 6": {
                "candidates_excluded": {
                    "0": "1",
                    "1": "3",
                    "2": "4",
                    "3": "6",
                    "4": "7",
                    "5": "8"
                },
                "scores_after_exclusion": {
                    "2": 289,
                    "5": 288
                },
                "scores_after_surplus": {
                    "2": 289,
                    "5": 288
                },
                "outcomes_scores": {
                    "3": 288,
                    "6": 289
                }
            },
            "Outcome N° 3 compared to Outcome N° 7": {
                "candidates_excluded": {
                    "0": "2",
                    "1": "3",
                    "2": "4",
                    "3": "6",
                    "4": "7",
                    "5": "8"
                },
                "scores_after_exclusion": {
                    "1": 232,
                    "5": 319
                },
                "scores_after_surplus": {
                    "1": 232,
                    "5": 319
                },
                "outcomes_scores": {
                    "3": 319,
                    "7": 232
                }
            },
            "Outcome N° 4 compared to Outcome N° 5": {
                "candidates_excluded": {
                    "0": "1",
                    "1": "2",
                    "2": "5",
                    "3": "6",
                    "4": "7",
                    "5": "8"
                },
                "scores_after_exclusion": {
                    "3": 290,
                    "4": 178
                },
                "scores_after_surplus": {
                    "3": 290,
                    "4": 178
                },
                "outcomes_scores": {
                    "4": 178,
                    "5": 290
                }
            },
            "Outcome N° 4 compared to Outcome N° 6": {
                "candidates_excluded": {
                    "0": "1",
                    "1": "3",
                    "2": "5",
                    "3": "6",
                    "4": "7",
                    "5": "8"
                },
                "scores_after_exclusion": {
                    "2": 348,
                    "4": 152
                },
                "scores_after_surplus": {
                    "2": 348,
                    "4": 152
                },
                "outcomes_scores": {
                    "4": 152,
                    "6": 348
                }
            },
            "Outcome N° 4 compared to Outcome N° 7": {
                "candidates_excluded": {
                    "0": "2",
                    "1": "3",
                    "2": "5",
                    "3": "6",
                    "4": "7",
                    "5": "8"
                },
                "scores_after_exclusion": {
                    "1": 278,
                    "4": 162
                },
                "scores_after_surplus": {
                    "1": 278,
                    "4": 162
                },
                "outcomes_scores": {
                    "4": 162,
                    "7": 278
                }
            },
            "Outcome N° 5 compared to Outcome N° 6": {
                "candidates_excluded": {
                    "0": "1",
                    "1": "4",
                    "2": "5",
                    "3": "6",
                    "4": "7",
                    "5": "8"
                },
                "scores_after_exclusion": {
                    "2": 321,
                    "3": 217
                },
                "scores_after_surplus": {
                    "2": 321,
                    "3": 217
                },
                "outcomes_scores": {
                    "5": 217,
                    "6": 321
                }
            },
            "Outcome N° 5 compared to Outcome N° 7": {
                "candidates_excluded": {
                    "0": "2",
                    "1": "4",
                    "2": "5",
                    "3": "6",
                    "4": "7",
                    "5": "8"
                },
                "scores_after_exclusion": {
                    "1": 271,
                    "3": 214
                },
                "scores_after_surplus": {
                    "1": 271,
                    "3": 214
                },
                "outcomes_scores": {
                    "5": 214,
                    "7": 271
                }
            },
            "Outcome N° 6 compared to Outcome N° 7": {
                "candidates_excluded": {
                    "0": "3",
                    "1": "4",
                    "2": "5",
                    "3": "6",
                    "4": "7",
                    "5": "8"
                },
                "scores_after_exclusion": {
                    "1": 232,
                    "2": 300
                },
                "scores_after_surplus": {
                    "1": 232,
                    "2": 300
                },
                "outcomes_scores": {
                    "6": 300,
                    "7": 232
                }
            }
        }
    }
}