{
    "Ranking": "Jonathan Carter > Hideki Yamane > None of the above > Felix Lechner",
    "Number Of Seats": 1,
    "Stats": {
        "Felix Lechner": {
            "Jonathan Carter": 0,
            "Hideki Yamane": 0,
            "None of the above": 0
        },
        "Jonathan Carter": {
            "Felix Lechner": 5.653846153846154,
            "Hideki Yamane": 3.8550724637681157,
            "None of the above": 14.863636363636363
        },
        "Hideki Yamane": {
            "Felix Lechner": 2.7261904761904763,
            "Jonathan Carter": 0,
            "None of the above": 5.471698113207547
        },
        "None of the above": {
            "Felix Lechner": 1.2450331125827814,
            "Jonathan Carter": 0,
            "Hideki Yamane": 0
        }
    }
}