{
    "Ranking": "1 > 3 > 1",
    "Number Of Seats": 3,
    "Stats": {
        "Rounds": {
            "1": {
                "1": {
                    "Quotient": 23,
                    "NumberOfSeatsAllocatedBeforeRound": 0
                },
                "2": {
                    "Quotient": 3,
                    "NumberOfSeatsAllocatedBeforeRound": 0
                },
                "3": {
                    "Quotient": 18,
                    "NumberOfSeatsAllocatedBeforeRound": 0
                },
                "4": {
                    "Quotient": 5,
                    "NumberOfSeatsAllocatedBeforeRound": 0
                }
            },
            "2": {
                "1": {
                    "Quotient": 11.5,
                    "NumberOfSeatsAllocatedBeforeRound": 1
                },
                "2": {
                    "Quotient": 3,
                    "NumberOfSeatsAllocatedBeforeRound": 0
                },
                "3": {
                    "Quotient": 18,
                    "NumberOfSeatsAllocatedBeforeRound": 0
                },
                "4": {
                    "Quotient": 5,
                    "NumberOfSeatsAllocatedBeforeRound": 0
                }
            },
            "3": {
                "1": {
                    "Quotient": 11.5,
                    "NumberOfSeatsAllocatedBeforeRound": 1
                },
                "2": {
                    "Quotient": 3,
                    "NumberOfSeatsAllocatedBeforeRound": 0
                },
                "3": {
                    "Quotient": 9,
                    "NumberOfSeatsAllocatedBeforeRound": 1
                },
                "4": {
                    "Quotient": 5,
                    "NumberOfSeatsAllocatedBeforeRound": 0
                }
            }
        },
        "Seats per Candidates": {
            "1": 2,
            "2": 0,
            "3": 1,
            "4": 0
        }
    }
}