{
    "Ranking": "Martin Michlmayr > Branden Robinson > Bdale Garbee > None Of The Above > Moshe Zadka",
    "Number Of Seats": 1,
    "Stats": {
        "bestScore": 2674,
        "rankingScore": {
            "0": {
                "1": "Moshe Zadka",
                "2": "Bdale Garbee",
                "3": "Branden Robinson",
                "4": "Martin Michlmayr",
                "5": "None Of The Above",
                "score": 1778
            },
            "1": {
                "1": "Moshe Zadka",
                "2": "Bdale Garbee",
                "3": "Branden Robinson",
                "4": "None Of The Above",
                "5": "Martin Michlmayr",
                "score": 1489
            },
            "2": {
                "1": "Moshe Zadka",
                "2": "Bdale Garbee",
                "3": "Martin Michlmayr",
                "4": "Branden Robinson",
                "5": "None Of The Above",
                "score": 1789
            },
            "3": {
                "1": "Moshe Zadka",
                "2": "Bdale Garbee",
                "3": "Martin Michlmayr",
                "4": "None Of The Above",
                "5": "Branden Robinson",
                "score": 1545
            },
            "4": {
                "1": "Moshe Zadka",
                "2": "Bdale Garbee",
                "3": "None Of The Above",
                "4": "Branden Robinson",
                "5": "Martin Michlmayr",
                "score": 1245
            },
            "5": {
                "1": "Moshe Zadka",
                "2": "Bdale Garbee",
                "3": "None Of The Above",
                "4": "Martin Michlmayr",
                "5": "Branden Robinson",
                "score": 1256
            },
            "6": {
                "1": "Moshe Zadka",
                "2": "Branden Robinson",
                "3": "Bdale Garbee",
                "4": "Martin Michlmayr",
                "5": "None Of The Above",
                "score": 1781
            },
            "7": {
                "1": "Moshe Zadka",
                "2": "Branden Robinson",
                "3": "Bdale Garbee",
                "4": "None Of The Above",
                "5": "Martin Michlmayr",
                "score": 1492
            },
            "8": {
                "1": "Moshe Zadka",
                "2": "Branden Robinson",
                "3": "Martin Michlmayr",
                "4": "Bdale Garbee",
                "5": "None Of The Above",
                "score": 1805
            },
            "9": {
                "1": "Moshe Zadka",
                "2": "Branden Robinson",
                "3": "Martin Michlmayr",
                "4": "None Of The Above",
                "5": "Bdale Garbee",
                "score": 1501
            },
            "10": {
                "1": "Moshe Zadka",
                "2": "Branden Robinson",
                "3": "None Of The Above",
                "4": "Bdale Garbee",
                "5": "Martin Michlmayr",
                "score": 1188
            },
            "11": {
                "1": "Moshe Zadka",
                "2": "Branden Robinson",
                "3": "None Of The Above",
                "4": "Martin Michlmayr",
                "5": "Bdale Garbee",
                "score": 1212
            },
            "12": {
                "1": "Moshe Zadka",
                "2": "Martin Michlmayr",
                "3": "Bdale Garbee",
                "4": "Branden Robinson",
                "5": "None Of The Above",
                "score": 1813
            },
            "13": {
                "1": "Moshe Zadka",
                "2": "Martin Michlmayr",
                "3": "Bdale Garbee",
                "4": "None Of The Above",
                "5": "Branden Robinson",
                "score": 1569
            },
            "14": {
                "1": "Moshe Zadka",
                "2": "Martin Michlmayr",
                "3": "Branden Robinson",
                "4": "Bdale Garbee",
                "5": "None Of The Above",
                "score": 1816
            },
            "15": {
                "1": "Moshe Zadka",
                "2": "Martin Michlmayr",
                "3": "Branden Robinson",
                "4": "None Of The Above",
                "5": "Bdale Garbee",
                "score": 1512
            },
            "16": {
                "1": "Moshe Zadka",
                "2": "Martin Michlmayr",
                "3": "None Of The Above",
                "4": "Bdale Garbee",
                "5": "Branden Robinson",
                "score": 1265
            },
            "17": {
                "1": "Moshe Zadka",
                "2": "Martin Michlmayr",
                "3": "None Of The Above",
                "4": "Branden Robinson",
                "5": "Bdale Garbee",
                "score": 1268
            },
            "18": {
                "1": "Moshe Zadka",
                "2": "None Of The Above",
                "3": "Bdale Garbee",
                "4": "Branden Robinson",
                "5": "Martin Michlmayr",
                "score": 941
            },
            "19": {
                "1": "Moshe Zadka",
                "2": "None Of The Above",
                "3": "Bdale Garbee",
                "4": "Martin Michlmayr",
                "5": "Branden Robinson",
                "score": 952
            },
            "20": {
                "1": "Moshe Zadka",
                "2": "None Of The Above",
                "3": "Branden Robinson",
                "4": "Bdale Garbee",
                "5": "Martin Michlmayr",
                "score": 944
            },
            "21": {
                "1": "Moshe Zadka",
                "2": "None Of The Above",
                "3": "Branden Robinson",
                "4": "Martin Michlmayr",
                "5": "Bdale Garbee",
                "score": 968
            },
            "22": {
                "1": "Moshe Zadka",
                "2": "None Of The Above",
                "3": "Martin Michlmayr",
                "4": "Bdale Garbee",
                "5": "Branden Robinson",
                "score": 976
            },
            "23": {
                "1": "Moshe Zadka",
                "2": "None Of The Above",
                "3": "Martin Michlmayr",
                "4": "Branden Robinson",
                "5": "Bdale Garbee",
                "score": 979
            },
            "24": {
                "1": "Bdale Garbee",
                "2": "Moshe Zadka",
                "3": "Branden Robinson",
                "4": "Martin Michlmayr",
                "5": "None Of The Above",
                "score": 2086
            },
            "25": {
                "1": "Bdale Garbee",
                "2": "Moshe Zadka",
                "3": "Branden Robinson",
                "4": "None Of The Above",
                "5": "Martin Michlmayr",
                "score": 1797
            },
            "26": {
                "1": "Bdale Garbee",
                "2": "Moshe Zadka",
                "3": "Martin Michlmayr",
                "4": "Branden Robinson",
                "5": "None Of The Above",
                "score": 2097
            },
            "27": {
                "1": "Bdale Garbee",
                "2": "Moshe Zadka",
                "3": "Martin Michlmayr",
                "4": "None Of The Above",
                "5": "Branden Robinson",
                "score": 1853
            },
            "28": {
                "1": "Bdale Garbee",
                "2": "Moshe Zadka",
                "3": "None Of The Above",
                "4": "Branden Robinson",
                "5": "Martin Michlmayr",
                "score": 1553
            },
            "29": {
                "1": "Bdale Garbee",
                "2": "Moshe Zadka",
                "3": "None Of The Above",
                "4": "Martin Michlmayr",
                "5": "Branden Robinson",
                "score": 1564
            },
            "30": {
                "1": "Bdale Garbee",
                "2": "Branden Robinson",
                "3": "Moshe Zadka",
                "4": "Martin Michlmayr",
                "5": "None Of The Above",
                "score": 2339
            },
            "31": {
                "1": "Bdale Garbee",
                "2": "Branden Robinson",
                "3": "Moshe Zadka",
                "4": "None Of The Above",
                "5": "Martin Michlmayr",
                "score": 2050
            },
            "32": {
                "1": "Bdale Garbee",
                "2": "Branden Robinson",
                "3": "Martin Michlmayr",
                "4": "Moshe Zadka",
                "5": "None Of The Above",
                "score": 2632
            },
            "33": {
                "1": "Bdale Garbee",
                "2": "Branden Robinson",
                "3": "Martin Michlmayr",
                "4": "None Of The Above",
                "5": "Moshe Zadka",
                "score": 2636
            },
            "34": {
                "1": "Bdale Garbee",
                "2": "Branden Robinson",
                "3": "None Of The Above",
                "4": "Moshe Zadka",
                "5": "Martin Michlmayr",
                "score": 2054
            },
            "35": {
                "1": "Bdale Garbee",
                "2": "Branden Robinson",
                "3": "None Of The Above",
                "4": "Martin Michlmayr",
                "5": "Moshe Zadka",
                "score": 2347
            },
            "36": {
                "1": "Bdale Garbee",
                "2": "Martin Michlmayr",
                "3": "Moshe Zadka",
                "4": "Branden Robinson",
                "5": "None Of The Above",
                "score": 2390
            },
            "37": {
                "1": "Bdale Garbee",
                "2": "Martin Michlmayr",
                "3": "Moshe Zadka",
                "4": "None Of The Above",
                "5": "Branden Robinson",
                "score": 2146
            },
            "38": {
                "1": "Bdale Garbee",
                "2": "Martin Michlmayr",
                "3": "Branden Robinson",
                "4": "Moshe Zadka",
                "5": "None Of The Above",
                "score": 2643
            },
            "39": {
                "1": "Bdale Garbee",
                "2": "Martin Michlmayr",
                "3": "Branden Robinson",
                "4": "None Of The Above",
                "5": "Moshe Zadka",
                "score": 2647
            },
            "40": {
                "1": "Bdale Garbee",
                "2": "Martin Michlmayr",
                "3": "None Of The Above",
                "4": "Moshe Zadka",
                "5": "Branden Robinson",
                "score": 2150
            },
            "41": {
                "1": "Bdale Garbee",
                "2": "Martin Michlmayr",
                "3": "None Of The Above",
                "4": "Branden Robinson",
                "5": "Moshe Zadka",
                "score": 2403
            },
            "42": {
                "1": "Bdale Garbee",
                "2": "None Of The Above",
                "3": "Moshe Zadka",
                "4": "Branden Robinson",
                "5": "Martin Michlmayr",
                "score": 1557
            },
            "43": {
                "1": "Bdale Garbee",
                "2": "None Of The Above",
                "3": "Moshe Zadka",
                "4": "Martin Michlmayr",
                "5": "Branden Robinson",
                "score": 1568
            },
            "44": {
                "1": "Bdale Garbee",
                "2": "None Of The Above",
                "3": "Branden Robinson",
                "4": "Moshe Zadka",
                "5": "Martin Michlmayr",
                "score": 1810
            },
            "45": {
                "1": "Bdale Garbee",
                "2": "None Of The Above",
                "3": "Branden Robinson",
                "4": "Martin Michlmayr",
                "5": "Moshe Zadka",
                "score": 2103
            },
            "46": {
                "1": "Bdale Garbee",
                "2": "None Of The Above",
                "3": "Martin Michlmayr",
                "4": "Moshe Zadka",
                "5": "Branden Robinson",
                "score": 1861
            },
            "47": {
                "1": "Bdale Garbee",
                "2": "None Of The Above",
                "3": "Martin Michlmayr",
                "4": "Branden Robinson",
                "5": "Moshe Zadka",
                "score": 2114
            },
            "48": {
                "1": "Branden Robinson",
                "2": "Moshe Zadka",
                "3": "Bdale Garbee",
                "4": "Martin Michlmayr",
                "5": "None Of The Above",
                "score": 2034
            },
            "49": {
                "1": "Branden Robinson",
                "2": "Moshe Zadka",
                "3": "Bdale Garbee",
                "4": "None Of The Above",
                "5": "Martin Michlmayr",
                "score": 1745
            },
            "50": {
                "1": "Branden Robinson",
                "2": "Moshe Zadka",
                "3": "Martin Michlmayr",
                "4": "Bdale Garbee",
                "5": "None Of The Above",
                "score": 2058
            },
            "51": {
                "1": "Branden Robinson",
                "2": "Moshe Zadka",
                "3": "Martin Michlmayr",
                "4": "None Of The Above",
                "5": "Bdale Garbee",
                "score": 1754
            },
            "52": {
                "1": "Branden Robinson",
                "2": "Moshe Zadka",
                "3": "None Of The Above",
                "4": "Bdale Garbee",
                "5": "Martin Michlmayr",
                "score": 1441
            },
            "53": {
                "1": "Branden Robinson",
                "2": "Moshe Zadka",
                "3": "None Of The Above",
                "4": "Martin Michlmayr",
                "5": "Bdale Garbee",
                "score": 1465
            },
            "54": {
                "1": "Branden Robinson",
                "2": "Bdale Garbee",
                "3": "Moshe Zadka",
                "4": "Martin Michlmayr",
                "5": "None Of The Above",
                "score": 2342
            },
            "55": {
                "1": "Branden Robinson",
                "2": "Bdale Garbee",
                "3": "Moshe Zadka",
                "4": "None Of The Above",
                "5": "Martin Michlmayr",
                "score": 2053
            },
            "56": {
                "1": "Branden Robinson",
                "2": "Bdale Garbee",
                "3": "Martin Michlmayr",
                "4": "Moshe Zadka",
                "5": "None Of The Above",
                "score": 2635
            },
            "57": {
                "1": "Branden Robinson",
                "2": "Bdale Garbee",
                "3": "Martin Michlmayr",
                "4": "None Of The Above",
                "5": "Moshe Zadka",
                "score": 2639
            },
            "58": {
                "1": "Branden Robinson",
                "2": "Bdale Garbee",
                "3": "None Of The Above",
                "4": "Moshe Zadka",
                "5": "Martin Michlmayr",
                "score": 2057
            },
            "59": {
                "1": "Branden Robinson",
                "2": "Bdale Garbee",
                "3": "None Of The Above",
                "4": "Martin Michlmayr",
                "5": "Moshe Zadka",
                "score": 2350
            },
            "60": {
                "1": "Branden Robinson",
                "2": "Martin Michlmayr",
                "3": "Moshe Zadka",
                "4": "Bdale Garbee",
                "5": "None Of The Above",
                "score": 2351
            },
            "61": {
                "1": "Branden Robinson",
                "2": "Martin Michlmayr",
                "3": "Moshe Zadka",
                "4": "None Of The Above",
                "5": "Bdale Garbee",
                "score": 2047
            },
            "62": {
                "1": "Branden Robinson",
                "2": "Martin Michlmayr",
                "3": "Bdale Garbee",
                "4": "Moshe Zadka",
                "5": "None Of The Above",
                "score": 2659
            },
            "63": {
                "1": "Branden Robinson",
                "2": "Martin Michlmayr",
                "3": "Bdale Garbee",
                "4": "None Of The Above",
                "5": "Moshe Zadka",
                "score": 2663
            },
            "64": {
                "1": "Branden Robinson",
                "2": "Martin Michlmayr",
                "3": "None Of The Above",
                "4": "Moshe Zadka",
                "5": "Bdale Garbee",
                "score": 2051
            },
            "65": {
                "1": "Branden Robinson",
                "2": "Martin Michlmayr",
                "3": "None Of The Above",
                "4": "Bdale Garbee",
                "5": "Moshe Zadka",
                "score": 2359
            },
            "66": {
                "1": "Branden Robinson",
                "2": "None Of The Above",
                "3": "Moshe Zadka",
                "4": "Bdale Garbee",
                "5": "Martin Michlmayr",
                "score": 1445
            },
            "67": {
                "1": "Branden Robinson",
                "2": "None Of The Above",
                "3": "Moshe Zadka",
                "4": "Martin Michlmayr",
                "5": "Bdale Garbee",
                "score": 1469
            },
            "68": {
                "1": "Branden Robinson",
                "2": "None Of The Above",
                "3": "Bdale Garbee",
                "4": "Moshe Zadka",
                "5": "Martin Michlmayr",
                "score": 1753
            },
            "69": {
                "1": "Branden Robinson",
                "2": "None Of The Above",
                "3": "Bdale Garbee",
                "4": "Martin Michlmayr",
                "5": "Moshe Zadka",
                "score": 2046
            },
            "70": {
                "1": "Branden Robinson",
                "2": "None Of The Above",
                "3": "Martin Michlmayr",
                "4": "Moshe Zadka",
                "5": "Bdale Garbee",
                "score": 1762
            },
            "71": {
                "1": "Branden Robinson",
                "2": "None Of The Above",
                "3": "Martin Michlmayr",
                "4": "Bdale Garbee",
                "5": "Moshe Zadka",
                "score": 2070
            },
            "72": {
                "1": "Martin Michlmayr",
                "2": "Moshe Zadka",
                "3": "Bdale Garbee",
                "4": "Branden Robinson",
                "5": "None Of The Above",
                "score": 2106
            },
            "73": {
                "1": "Martin Michlmayr",
                "2": "Moshe Zadka",
                "3": "Bdale Garbee",
                "4": "None Of The Above",
                "5": "Branden Robinson",
                "score": 1862
            },
            "74": {
                "1": "Martin Michlmayr",
                "2": "Moshe Zadka",
                "3": "Branden Robinson",
                "4": "Bdale Garbee",
                "5": "None Of The Above",
                "score": 2109
            },
            "75": {
                "1": "Martin Michlmayr",
                "2": "Moshe Zadka",
                "3": "Branden Robinson",
                "4": "None Of The Above",
                "5": "Bdale Garbee",
                "score": 1805
            },
            "76": {
                "1": "Martin Michlmayr",
                "2": "Moshe Zadka",
                "3": "None Of The Above",
                "4": "Bdale Garbee",
                "5": "Branden Robinson",
                "score": 1558
            },
            "77": {
                "1": "Martin Michlmayr",
                "2": "Moshe Zadka",
                "3": "None Of The Above",
                "4": "Branden Robinson",
                "5": "Bdale Garbee",
                "score": 1561
            },
            "78": {
                "1": "Martin Michlmayr",
                "2": "Bdale Garbee",
                "3": "Moshe Zadka",
                "4": "Branden Robinson",
                "5": "None Of The Above",
                "score": 2414
            },
            "79": {
                "1": "Martin Michlmayr",
                "2": "Bdale Garbee",
                "3": "Moshe Zadka",
                "4": "None Of The Above",
                "5": "Branden Robinson",
                "score": 2170
            },
            "80": {
                "1": "Martin Michlmayr",
                "2": "Bdale Garbee",
                "3": "Branden Robinson",
                "4": "Moshe Zadka",
                "5": "None Of The Above",
                "score": 2667
            },
            "81": {
                "1": "Martin Michlmayr",
                "2": "Bdale Garbee",
                "3": "Branden Robinson",
                "4": "None Of The Above",
                "5": "Moshe Zadka",
                "score": 2671
            },
            "82": {
                "1": "Martin Michlmayr",
                "2": "Bdale Garbee",
                "3": "None Of The Above",
                "4": "Moshe Zadka",
                "5": "Branden Robinson",
                "score": 2174
            },
            "83": {
                "1": "Martin Michlmayr",
                "2": "Bdale Garbee",
                "3": "None Of The Above",
                "4": "Branden Robinson",
                "5": "Moshe Zadka",
                "score": 2427
            },
            "84": {
                "1": "Martin Michlmayr",
                "2": "Branden Robinson",
                "3": "Moshe Zadka",
                "4": "Bdale Garbee",
                "5": "None Of The Above",
                "score": 2362
            },
            "85": {
                "1": "Martin Michlmayr",
                "2": "Branden Robinson",
                "3": "Moshe Zadka",
                "4": "None Of The Above",
                "5": "Bdale Garbee",
                "score": 2058
            },
            "86": {
                "1": "Martin Michlmayr",
                "2": "Branden Robinson",
                "3": "Bdale Garbee",
                "4": "Moshe Zadka",
                "5": "None Of The Above",
                "score": 2670
            },
            "87": {
                "1": "Martin Michlmayr",
                "2": "Branden Robinson",
                "3": "Bdale Garbee",
                "4": "None Of The Above",
                "5": "Moshe Zadka",
                "score": 2674
            },
            "88": {
                "1": "Martin Michlmayr",
                "2": "Branden Robinson",
                "3": "None Of The Above",
                "4": "Moshe Zadka",
                "5": "Bdale Garbee",
                "score": 2062
            },
            "89": {
                "1": "Martin Michlmayr",
                "2": "Branden Robinson",
                "3": "None Of The Above",
                "4": "Bdale Garbee",
                "5": "Moshe Zadka",
                "score": 2370
            },
            "90": {
                "1": "Martin Michlmayr",
                "2": "None Of The Above",
                "3": "Moshe Zadka",
                "4": "Bdale Garbee",
                "5": "Branden Robinson",
                "score": 1562
            },
            "91": {
                "1": "Martin Michlmayr",
                "2": "None Of The Above",
                "3": "Moshe Zadka",
                "4": "Branden Robinson",
                "5": "Bdale Garbee",
                "score": 1565
            },
            "92": {
                "1": "Martin Michlmayr",
                "2": "None Of The Above",
                "3": "Bdale Garbee",
                "4": "Moshe Zadka",
                "5": "Branden Robinson",
                "score": 1870
            },
            "93": {
                "1": "Martin Michlmayr",
                "2": "None Of The Above",
                "3": "Bdale Garbee",
                "4": "Branden Robinson",
                "5": "Moshe Zadka",
                "score": 2123
            },
            "94": {
                "1": "Martin Michlmayr",
                "2": "None Of The Above",
                "3": "Branden Robinson",
                "4": "Moshe Zadka",
                "5": "Bdale Garbee",
                "score": 1818
            },
            "95": {
                "1": "Martin Michlmayr",
                "2": "None Of The Above",
                "3": "Branden Robinson",
                "4": "Bdale Garbee",
                "5": "Moshe Zadka",
                "score": 2126
            },
            "96": {
                "1": "None Of The Above",
                "2": "Moshe Zadka",
                "3": "Bdale Garbee",
                "4": "Branden Robinson",
                "5": "Martin Michlmayr",
                "score": 945
            },
            "97": {
                "1": "None Of The Above",
                "2": "Moshe Zadka",
                "3": "Bdale Garbee",
                "4": "Martin Michlmayr",
                "5": "Branden Robinson",
                "score": 956
            },
            "98": {
                "1": "None Of The Above",
                "2": "Moshe Zadka",
                "3": "Branden Robinson",
                "4": "Bdale Garbee",
                "5": "Martin Michlmayr",
                "score": 948
            },
            "99": {
                "1": "None Of The Above",
                "2": "Moshe Zadka",
                "3": "Branden Robinson",
                "4": "Martin Michlmayr",
                "5": "Bdale Garbee",
                "score": 972
            },
            "100": {
                "1": "None Of The Above",
                "2": "Moshe Zadka",
                "3": "Martin Michlmayr",
                "4": "Bdale Garbee",
                "5": "Branden Robinson",
                "score": 980
            },
            "101": {
                "1": "None Of The Above",
                "2": "Moshe Zadka",
                "3": "Martin Michlmayr",
                "4": "Branden Robinson",
                "5": "Bdale Garbee",
                "score": 983
            },
            "102": {
                "1": "None Of The Above",
                "2": "Bdale Garbee",
                "3": "Moshe Zadka",
                "4": "Branden Robinson",
                "5": "Martin Michlmayr",
                "score": 1253
            },
            "103": {
                "1": "None Of The Above",
                "2": "Bdale Garbee",
                "3": "Moshe Zadka",
                "4": "Martin Michlmayr",
                "5": "Branden Robinson",
                "score": 1264
            },
            "104": {
                "1": "None Of The Above",
                "2": "Bdale Garbee",
                "3": "Branden Robinson",
                "4": "Moshe Zadka",
                "5": "Martin Michlmayr",
                "score": 1506
            },
            "105": {
                "1": "None Of The Above",
                "2": "Bdale Garbee",
                "3": "Branden Robinson",
                "4": "Martin Michlmayr",
                "5": "Moshe Zadka",
                "score": 1799
            },
            "106": {
                "1": "None Of The Above",
                "2": "Bdale Garbee",
                "3": "Martin Michlmayr",
                "4": "Moshe Zadka",
                "5": "Branden Robinson",
                "score": 1557
            },
            "107": {
                "1": "None Of The Above",
                "2": "Bdale Garbee",
                "3": "Martin Michlmayr",
                "4": "Branden Robinson",
                "5": "Moshe Zadka",
                "score": 1810
            },
            "108": {
                "1": "None Of The Above",
                "2": "Branden Robinson",
                "3": "Moshe Zadka",
                "4": "Bdale Garbee",
                "5": "Martin Michlmayr",
                "score": 1201
            },
            "109": {
                "1": "None Of The Above",
                "2": "Branden Robinson",
                "3": "Moshe Zadka",
                "4": "Martin Michlmayr",
                "5": "Bdale Garbee",
                "score": 1225
            },
            "110": {
                "1": "None Of The Above",
                "2": "Branden Robinson",
                "3": "Bdale Garbee",
                "4": "Moshe Zadka",
                "5": "Martin Michlmayr",
                "score": 1509
            },
            "111": {
                "1": "None Of The Above",
                "2": "Branden Robinson",
                "3": "Bdale Garbee",
                "4": "Martin Michlmayr",
                "5": "Moshe Zadka",
                "score": 1802
            },
            "112": {
                "1": "None Of The Above",
                "2": "Branden Robinson",
                "3": "Martin Michlmayr",
                "4": "Moshe Zadka",
                "5": "Bdale Garbee",
                "score": 1518
            },
            "113": {
                "1": "None Of The Above",
                "2": "Branden Robinson",
                "3": "Martin Michlmayr",
                "4": "Bdale Garbee",
                "5": "Moshe Zadka",
                "score": 1826
            },
            "114": {
                "1": "None Of The Above",
                "2": "Martin Michlmayr",
                "3": "Moshe Zadka",
                "4": "Bdale Garbee",
                "5": "Branden Robinson",
                "score": 1273
            },
            "115": {
                "1": "None Of The Above",
                "2": "Martin Michlmayr",
                "3": "Moshe Zadka",
                "4": "Branden Robinson",
                "5": "Bdale Garbee",
                "score": 1276
            },
            "116": {
                "1": "None Of The Above",
                "2": "Martin Michlmayr",
                "3": "Bdale Garbee",
                "4": "Moshe Zadka",
                "5": "Branden Robinson",
                "score": 1581
            },
            "117": {
                "1": "None Of The Above",
                "2": "Martin Michlmayr",
                "3": "Bdale Garbee",
                "4": "Branden Robinson",
                "5": "Moshe Zadka",
                "score": 1834
            },
            "118": {
                "1": "None Of The Above",
                "2": "Martin Michlmayr",
                "3": "Branden Robinson",
                "4": "Moshe Zadka",
                "5": "Bdale Garbee",
                "score": 1529
            },
            "119": {
                "1": "None Of The Above",
                "2": "Martin Michlmayr",
                "3": "Branden Robinson",
                "4": "Bdale Garbee",
                "5": "Moshe Zadka",
                "score": 1837
            }
        }
    }
}